Workbook

Sheet Dashboard
B2: HXP Parent Builder Survey — Dashboard
B3: 1,189 parent responses collected before this year's trips
B5: =COUNTA(Insights!A2:A1190) | E5: =COUNTIF(Insights!A2:A1190,"Yes")/COUNTA(Insights!A2:A1190) | H5: =COUNTIF(Insights!A2:A1190,"No")/COUNTA(Insights!A2:A1190) | K5: =(COUNTIF(Insights!I2:I1190,"HXP Can Directly Fix")+COUNTIF(Insights!I2:I1190,"HXP Can Influence"))/SUM('Chart Data'!B38:B41) | N5: =COUNTIF(Insights!J2:J1190,TRUE)
B8: Total Responses | E8: Planning to Go (Yes) | H8: Not Going (No) | K8: "No" Reasons HXP Can Control | N8: Warm Leads (Soft 'No' Signal)
B47: Sample "Warm Lead" Quotes (parents who said no, but hinted they'd reconsider)
B48: “My job and time off. I would really love to go another year.”
B49: “Other obligations this year, but I hope to go in the future!”
B50: “My daughter needs the experience without me. But I would love to go!”
B51: “I would really like to go in the future. I am sending 3 teens this year. Finance is a part of why I am not going. And then it would be tough for me...”
B52: “I went last year and loved it. I will go again next year.”

Sheet Chart Data
A1: Backing data for the Dashboard charts - safe to leave visible, not meant for managers to read directly.
A3: Why Parents Don't Go
A4: Category | B4: Count
A5: Cost / Finances | B5: =COUNTIF(Insights!$F$2:$F$1190,"Cost / Finances")
A6: Work Schedule / Time Off | B6: =COUNTIF(Insights!$F$2:$F$1190,"Work Schedule / Time Off")
A7: Wants Child to Have Independent Experience | B7: =COUNTIF(Insights!$F$2:$F$1190,"Wants Child to Have Independent Experience")
A8: Other Kids / Family at Home | B8: =COUNTIF(Insights!$F$2:$F$1190,"Other Kids / Family at Home")
A9: Child Didn't Want Parent to Come | B9: =COUNTIF(Insights!$F$2:$F$1190,"Child Didn't Want Parent to Come")
A10: Another Family Member Going Instead | B10: =COUNTIF(Insights!$F$2:$F$1190,"Another Family Member Going Instead")
A11: Other / Uncategorized | B11: =COUNTIF(Insights!$F$2:$F$1190,"Other / Uncategorized")
A12: Not a Traveler / Personal Preference | B12: =COUNTIF(Insights!$F$2:$F$1190,"Not a Traveler / Personal Preference")
A13: Not Aware It Was an Option | B13: =COUNTIF(Insights!$F$2:$F$1190,"Not Aware It Was an Option")
A14: Other Life Commitment | B14: =COUNTIF(Insights!$F$2:$F$1190,"Other Life Commitment")
A15: Health / Physical / Age | B15: =COUNTIF(Insights!$F$2:$F$1190,"Health / Physical / Age")
A16: Family's Own Choice (No Elaboration) | B16: =COUNTIF(Insights!$F$2:$F$1190,"Family's Own Choice (No Elaboration)")
A17: Trip / Spot Was Already Full | B17: =COUNTIF(Insights!$F$2:$F$1190,"Trip / Spot Was Already Full")
A18: Not Needed | B18: =COUNTIF(Insights!$F$2:$F$1190,"Not Needed")
A21: Why Parents Do Go
A22: Category | B22: Count
A23: Wanted Shared Experience with Child | B23: =COUNTIF(Insights!$C$2:$C$1190,"Wanted Shared Experience with Child")
A24: Previous Positive Experience | B24: =COUNTIF(Insights!$C$2:$C$1190,"Previous Positive Experience")
A25: Faith / Service Motivation | B25: =COUNTIF(Insights!$C$2:$C$1190,"Faith / Service Motivation")
A26: Child/Spouse Asked Them to Go | B26: =COUNTIF(Insights!$C$2:$C$1190,"Child/Spouse Asked Them to Go")
A27: Family Member Was the Reason (No Elaboration) | B27: =COUNTIF(Insights!$C$2:$C$1190,"Family Member Was the Reason (No Elaboration)")
A28: Other / Uncategorized | B28: =COUNTIF(Insights!$C$2:$C$1190,"Other / Uncategorized")
A29: Love of Travel / Culture | B29: =COUNTIF(Insights!$C$2:$C$1190,"Love of Travel / Culture")
A30: Trust in the HXP Program | B30: =COUNTIF(Insights!$C$2:$C$1190,"Trust in the HXP Program")
A31: Concerned About Child Going Alone / Safety | B31: =COUNTIF(Insights!$C$2:$C$1190,"Concerned About Child Going Alone / Safety")
A32: Securing/Ensuring Child's Spot (Registration Timing) | B32: =COUNTIF(Insights!$C$2:$C$1190,"Securing/Ensuring Child's Spot (Registration Timing)")
A33: Personally Invited by HXP Staff/Trip Leader | B33: =COUNTIF(Insights!$C$2:$C$1190,"Personally Invited by HXP Staff/Trip Leader")
A36: Controllability
A37: Bucket | B37: Count
A38: HXP Can Directly Fix | B38: =COUNTIF(Insights!$I$2:$I$1190,"HXP Can Directly Fix")
A39: HXP Can Influence | B39: =COUNTIF(Insights!$I$2:$I$1190,"HXP Can Influence")
A40: Family's Own Choice | B40: =COUNTIF(Insights!$I$2:$I$1190,"Family's Own Choice")
A41: Unknown | B41: =COUNTIF(Insights!$I$2:$I$1190,"Unknown")
A44: Would-Help Themes (Maybe segment)
A45: Theme | B45: Count
A46: Cost / Financial Assistance | B46: =COUNTIF(Insights!$L$2:$L$1190,"Cost / Financial Assistance")
A47: Time / Scheduling | B47: =COUNTIF(Insights!$L$2:$L$1190,"Time / Scheduling")
A48: Childcare for Other Kids | B48: =COUNTIF(Insights!$L$2:$L$1190,"Childcare for Other Kids")
A49: Waiting for Right Timing (kids' ages) | B49: =COUNTIF(Insights!$L$2:$L$1190,"Waiting for Right Timing (kids' ages)")
A50: Other / Uncategorized | B50: =COUNTIF(Insights!$L$2:$L$1190,"Other / Uncategorized")
A51: No Specific Ask / Undecided | B51: =COUNTIF(Insights!$L$2:$L$1190,"No Specific Ask / Undecided")
A52: More Information / Awareness | B52: =COUNTIF(Insights!$L$2:$L$1190,"More Information / Awareness")
A53: Health | B53: =COUNTIF(Insights!$L$2:$L$1190,"Health")
A54: Registration / Spot Availability | B54: =COUNTIF(Insights!$L$2:$L$1190,"Registration / Spot Availability")

Sheet Raw Data
A1: Are you planning on going as a Parent Builder? | B1: What influenced your decision to go? | C1: What influenced your decision not to go? | D1: What would help change your decision to go?
A2: No | C2: Good for my son to go without me.
A3: No | C3: Confidence in my kid
A4: No | C4: Not needed
A5: No | C5: I still have younger children to save for.
A6: No | C6: I think it is better for him
A7: No | C7: Want my son to have his own experience
A8: Yes | B8: I love teenagers, people in other cultures, and I love travel.
A9: Yes | B9: My husband wanted someone to go with our daughter, but I also wanted to experience this piece of heaven. I love teenagers!
A10: No | C10: The cost. Would have loved to go as a parent but it just wasn’t in our budget
A11: No | C11: Friends with experience
A12: Yes | B12: Could go with my son
A13: No | C13: Time away from work
A14: No | C14: Thought my daughter would have a better experience with out me
A15: No
A16: No
A17: No | C17: Our son needs an independent experience.
A18: No | C18: Money
A19: No | C19: I have 4 other kiddos at home that need me
A20: No | C20: cost
A21: No | C21: my daughter does not want me to go
A22: No | C22: Wanted my son to go alone
A23: No
A24: Yes | B24: My daughter asked me ro go
A25: No | C25: I want to fill up my time with something fun that makes me happy and is productive. I am also excited to experience the beauty of OBX
A26: No | C26: My job and time off. I would really love to go another year.
A27: No | C27: I wanted my daughter to have this experience on her own. I wanted her to rely on her group rather than me, to help her build stronger connections with other builders & the trip leaders.
A28: No | C28: Younger kids at home
A29: No | C29: Daughter asked me not to go
A30: No | C30: I really wanted to go, my son was cool with me going, but the Spirit said he needed to do this without me.
A31: No | C31: Work schedule is not compatible with the HXP schedule.
A32: No | C32: Cost & time away from other kids, also excited for my son to do this without me
A33: Maybe | D33: Cost
A34: No | C34: Private time for him
A35: No | C35: Work obligations
A36: No | C36: My child wanted to go on her own.
A37: Yes | B37: Previous trips
A38: No | C38: Time/ son coming home from a mission
A39: Yes | B39: I have been before and love it.
A40: Yes | B40: The Q&A night
A41: No | C41: My husband is going as the male parent builder
A42: No | C42: Time and money
A43: No
A44: No | C44: Just the timing with life and having other kids at home.
A45: No | C45: Other kids at home.
A46: No | C46: I want my son To have this experience alone.
A47: No | C47: Wanted my son to be on his own
A48: Maybe | D48: If it was less expensive
A49: No | C49: I wanted my daughter to have an experience where she needed to learn to rely on herself instead of her parents
A50: No | C50: $$, otherwise, I’d love to go. We could only afford for our youth to go.
A51: No | C51: I want my son to have an independent experience away from parents.
A52: No
A53: No | C53: My husband and I have both been trip builders before. Our son wanted the experience of going without parents :)
A54: No | C54: This is my son’s experience. He always has his parents in tow on church functions.
A55: No | C55: My child wanted to go alone
A56: No | C56: My child
A57: No | C57: I think my daughter was excited to do this on her own - without her dad or I having to be part of it.
A58: No | C58: Timing & cost
A59: No | C59: The expense
A60: No | C60: My daughter really wanted to have an independent experience and go on her own.
A61: No | C61: Wanting to let my son have his own experience
A62: No | C62: Time and money
A63: No | C63: Price
A64: No | C64: Availability
A65: Maybe
A66: No
A67: No | C67: My little kids at home.
A68: No | C68: My child wanted to go alone and I have younger children
A69: No | C69: Time away from work and wanted son to have his own experience.
A70: Yes | B70: My wife went with our son last year.
A71: No | C71: Wanted my daughter to have as much autonomy while on her trip.
A72: Yes | B72: Desire to spend time with my daughter doing something important, memorable and impactful.
A73: No | C73: Work obligations
A74: No | C74: Work
A75: No | C75: My child needed to do this without a parent
A76: No | C76: I don’t enjoy being responsible for other people’s kids
A77: Yes | B77: Desire to spend time with my son and to have an adventure.
A78: No
A79: No | C79: My daughter didn't want us to go
A80: No | C80: Personally not adventurous and comfortable
A81: Yes | B81: I wanted my son to go, and there was not a spot for him. The spot was freed up when I agreed to go as a parent builder. And I have a brother-in-law who went as a parent builder and had nothing but fantastic things to say about his experience.
A82: No | C82: We thought it would be a better experience for him to go alone
A83: No | C83: Big church callings have required us to always be at camps and other activities for our children. Our son needs a chance to be able to go out and experience life on his own without mom and dad there.
A84: No | C84: Busy schedule
A85: No | C85: can't make it work with kids at home
A86: No | C86: We wanted our daughter to have an experience on her own, I have been at every camp etc she has been to. :)
A87: No | C87: Other kids at home
A88: No | C88: Not the right season of my life. I still have little kids at home. I also think for my particular child she will have a better experience on her own.
A89: No | C89: Sibling had a great experience
A90: No | C90: Money. Also our child needs to learn to do things without his parents there.
A91: No | C91: To the parent expo? I must not have been paying attention because I didn't know about it.
A92: No | C92: I want my son to learn that he can be independent of me and have his own experience
A93: No | C93: I wanted my daughter to have an independent experience
A94: Yes | B94: My daughter wouldn't go with me
A95: No | C95: learning to know and serve people who are having a different life experience from us.
A96: No | C96: cost and family responsibility at home
A97: No | C97: Cost mainly. Also, we want our child to have an experience away from family.
A98: No | C98: My husband is going with our daughter instead
A99: No | C99: Time
A100: No | C100: money and time
...

Sheet Cleaned + Categorized
A1: Status | B1: Reason To Go | C1: Reason To Go - Category | D1: Reason To Go - All Tags | E1: Reason Not To Go | F1: Reason Not To Go - Category | G1: Reason Not To Go - All Tags | H1: What Would Help
A2: No | E2: Good for my son to go without me. | F2: Wants Child to Have Independent Experience | G2: Wants Child to Have Independent Experience
A3: No | E3: Confidence in my kid | F3: Wants Child to Have Independent Experience | G3: Wants Child to Have Independent Experience
A4: No | E4: Not needed | F4: Not Needed | G4: Not Needed
A5: No | E5: I still have younger children to save for. | F5: Other Kids / Family at Home | G5: Other Kids / Family at Home
A6: No | E6: I think it is better for him | F6: Wants Child to Have Independent Experience | G6: Wants Child to Have Independent Experience
A7: No | E7: Want my son to have his own experience | F7: Wants Child to Have Independent Experience | G7: Wants Child to Have Independent Experience
A8: Yes | B8: I love teenagers, people in other cultures, and I love travel. | C8: Love of Travel / Culture | D8: Love of Travel / Culture
A9: Yes | B9: My husband wanted someone to go with our daughter, but I also wanted to experience this piece of heaven. I love teenagers! | C9: Wanted Shared Experience with Child | D9: Wanted Shared Experience with Child
A10: No | E10: The cost. Would have loved to go as a parent but it just wasn't in our budget | F10: Cost / Finances | G10: Cost / Finances
A11: No | E11: Friends with experience | F11: Wants Child to Have Independent Experience | G11: Wants Child to Have Independent Experience
A12: Yes | B12: Could go with my son | C12: Other / Uncategorized
A13: No | E13: Time away from work | F13: Work Schedule / Time Off | G13: Work Schedule / Time Off
A14: No | E14: Thought my daughter would have a better experience with out me | F14: Wants Child to Have Independent Experience | G14: Wants Child to Have Independent Experience
A15: No
A16: No
A17: No | E17: Our son needs an independent experience. | F17: Wants Child to Have Independent Experience | G17: Wants Child to Have Independent Experience
A18: No | E18: Money | F18: Cost / Finances | G18: Cost / Finances
A19: No | E19: I have 4 other kiddos at home that need me | F19: Other Kids / Family at Home | G19: Other Kids / Family at Home
A20: No | E20: cost | F20: Cost / Finances | G20: Cost / Finances
A21: No | E21: my daughter does not want me to go | F21: Child Didn't Want Parent to Come | G21: Child Didn't Want Parent to Come
A22: No | E22: Wanted my son to go alone | F22: Wants Child to Have Independent Experience | G22: Wants Child to Have Independent Experience
A23: No
A24: Yes | B24: My daughter asked me ro go | C24: Child/Spouse Asked Them to Go | D24: Child/Spouse Asked Them to Go
A25: No | E25: I want to fill up my time with something fun that makes me happy and is productive. I am also excited to experience the beauty of OBX | F25: Work Schedule / Time Off | G25: Work Schedule / Time Off; Wants Child to Have Independent Experience
A26: No | E26: My job and time off. I would really love to go another year. | F26: Work Schedule / Time Off | G26: Work Schedule / Time Off
A27: No | E27: I wanted my daughter to have this experience on her own. I wanted her to rely on her group rather than me, to help her build stronger connections with other builders & the trip leaders. | F27: Wants Child to Have Independent Experience | G27: Wants Child to Have Independent Experience; Other Life Commitment
A28: No | E28: Younger kids at home | F28: Other Kids / Family at Home | G28: Other Kids / Family at Home
A29: No | E29: Daughter asked me not to go | F29: Child Didn't Want Parent to Come | G29: Child Didn't Want Parent to Come
A30: No | E30: I really wanted to go, my son was cool with me going, but the Spirit said he needed to do this without me. | F30: Wants Child to Have Independent Experience | G30: Wants Child to Have Independent Experience
A31: No | E31: Work schedule is not compatible with the HXP schedule. | F31: Work Schedule / Time Off | G31: Work Schedule / Time Off
A32: No | E32: Cost & time away from other kids, also excited for my son to do this without me | F32: Cost / Finances | G32: Cost / Finances; Work Schedule / Time Off; Other Kids / Family at Home; Wants Child to Have Independent Experience
A33: Maybe | H33: Cost
A34: No | E34: Private time for him | F34: Work Schedule / Time Off | G34: Work Schedule / Time Off
A35: No | E35: Work obligations | F35: Work Schedule / Time Off | G35: Work Schedule / Time Off
A36: No | E36: My child wanted to go on her own. | F36: Wants Child to Have Independent Experience | G36: Wants Child to Have Independent Experience
A37: Yes | B37: Previous trips | C37: Previous Positive Experience | D37: Previous Positive Experience
A38: No | E38: Time/ son coming home from a mission | F38: Work Schedule / Time Off | G38: Work Schedule / Time Off; Other Life Commitment
A39: Yes | B39: I have been before and love it. | C39: Previous Positive Experience | D39: Previous Positive Experience
A40: Yes | B40: The Q&A night | C40: Trust in the HXP Program | D40: Trust in the HXP Program
A41: No | E41: My husband is going as the male parent builder | F41: Another Family Member Going Instead | G41: Another Family Member Going Instead
A42: No | E42: Time and money | F42: Cost / Finances | G42: Cost / Finances; Work Schedule / Time Off
A43: No
A44: No | E44: Just the timing with life and having other kids at home. | F44: Work Schedule / Time Off | G44: Work Schedule / Time Off; Other Kids / Family at Home
A45: No | E45: Other kids at home. | F45: Other Kids / Family at Home | G45: Other Kids / Family at Home
A46: No | E46: I want my son To have this experience alone. | F46: Wants Child to Have Independent Experience | G46: Wants Child to Have Independent Experience
A47: No | E47: Wanted my son to be on his own | F47: Wants Child to Have Independent Experience | G47: Wants Child to Have Independent Experience
A48: Maybe | H48: If it was less expensive
A49: No | E49: I wanted my daughter to have an experience where she needed to learn to rely on herself instead of her parents | F49: Wants Child to Have Independent Experience | G49: Wants Child to Have Independent Experience
A50: No | E50: $$, otherwise, I'd love to go. We could only afford for our youth to go. | F50: Cost / Finances | G50: Cost / Finances
A51: No | E51: I want my son to have an independent experience away from parents. | F51: Wants Child to Have Independent Experience | G51: Wants Child to Have Independent Experience
A52: No
A53: No | E53: My husband and I have both been trip builders before. Our son wanted the experience of going without parents :) | F53: Wants Child to Have Independent Experience | G53: Wants Child to Have Independent Experience
A54: No | E54: This is my son's experience. He always has his parents in tow on church functions. | F54: Wants Child to Have Independent Experience | G54: Wants Child to Have Independent Experience
A55: No | E55: My child wanted to go alone | F55: Wants Child to Have Independent Experience | G55: Wants Child to Have Independent Experience
A56: No | E56: My child | F56: Family's Own Choice (No Elaboration) | G56: Family's Own Choice (No Elaboration)
A57: No | E57: I think my daughter was excited to do this on her own - without her dad or I having to be part of it. | F57: Wants Child to Have Independent Experience | G57: Wants Child to Have Independent Experience
A58: No | E58: Timing & cost | F58: Cost / Finances | G58: Cost / Finances; Work Schedule / Time Off
A59: No | E59: The expense | F59: Cost / Finances | G59: Cost / Finances
A60: No | E60: My daughter really wanted to have an independent experience and go on her own. | F60: Wants Child to Have Independent Experience | G60: Wants Child to Have Independent Experience
A61: No | E61: Wanting to let my son have his own experience | F61: Wants Child to Have Independent Experience | G61: Wants Child to Have Independent Experience
A62: No | E62: Time and money | F62: Cost / Finances | G62: Cost / Finances; Work Schedule / Time Off
A63: No | E63: Price | F63: Cost / Finances | G63: Cost / Finances
A64: No | E64: Availability | F64: Work Schedule / Time Off | G64: Work Schedule / Time Off
A65: Maybe
A66: No
A67: No | E67: My little kids at home. | F67: Other Kids / Family at Home | G67: Other Kids / Family at Home
A68: No | E68: My child wanted to go alone and I have younger children | F68: Other Kids / Family at Home | G68: Other Kids / Family at Home; Wants Child to Have Independent Experience
A69: No | E69: Time away from work and wanted son to have his own experience. | F69: Work Schedule / Time Off | G69: Work Schedule / Time Off; Wants Child to Have Independent Experience
A70: Yes | B70: My wife went with our son last year. | C70: Previous Positive Experience | D70: Previous Positive Experience
A71: No | E71: Wanted my daughter to have as much autonomy while on her trip. | F71: Wants Child to Have Independent Experience | G71: Wants Child to Have Independent Experience
A72: Yes | B72: Desire to spend time with my daughter doing something important, memorable and impactful. | C72: Wanted Shared Experience with Child | D72: Wanted Shared Experience with Child
A73: No | E73: Work obligations | F73: Work Schedule / Time Off | G73: Work Schedule / Time Off
A74: No | E74: Work | F74: Work Schedule / Time Off | G74: Work Schedule / Time Off
A75: No | E75: My child needed to do this without a parent | F75: Wants Child to Have Independent Experience | G75: Wants Child to Have Independent Experience
A76: No | E76: I don't enjoy being responsible for other people's kids | F76: Not a Traveler / Personal Preference | G76: Not a Traveler / Personal Preference
A77: Yes | B77: Desire to spend time with my son and to have an adventure. | C77: Wanted Shared Experience with Child | D77: Wanted Shared Experience with Child; Love of Travel / Culture
A78: No
A79: No | E79: My daughter didn't want us to go | F79: Child Didn't Want Parent to Come | G79: Child Didn't Want Parent to Come
A80: No | E80: Personally not adventurous and comfortable | F80: Not a Traveler / Personal Preference | G80: Not a Traveler / Personal Preference
A81: Yes | B81: I wanted my son to go, and there was not a spot for him. The spot was freed up when I agreed to go as a parent builder. And I have a brother-in-law who went as a parent builder and had nothing but fantastic things to say about his experience. | C81: Wanted Shared Experience with Child | D81: Wanted Shared Experience with Child
A82: No | E82: We thought it would be a better experience for him to go alone | F82: Wants Child to Have Independent Experience | G82: Wants Child to Have Independent Experience
A83: No | E83: Big church callings have required us to always be at camps and other activities for our children. Our son needs a chance to be able to go out and experience life on his own without mom and dad there. | F83: Wants Child to Have Independent Experience | G83: Wants Child to Have Independent Experience; Other Life Commitment
A84: No | E84: Busy schedule | F84: Work Schedule / Time Off | G84: Work Schedule / Time Off
A85: No | E85: can't make it work with kids at home | F85: Work Schedule / Time Off | G85: Work Schedule / Time Off; Other Kids / Family at Home
A86: No | E86: We wanted our daughter to have an experience on her own, I have been at every camp etc she has been to. :) | F86: Wants Child to Have Independent Experience | G86: Wants Child to Have Independent Experience
A87: No | E87: Other kids at home | F87: Other Kids / Family at Home | G87: Other Kids / Family at Home
A88: No | E88: Not the right season of my life. I still have little kids at home. I also think for my particular child she will have a better experience on her own. | F88: Other Kids / Family at Home | G88: Other Kids / Family at Home; Wants Child to Have Independent Experience
A89: No | E89: Sibling had a great experience | F89: Other Kids / Family at Home | G89: Other Kids / Family at Home; Wants Child to Have Independent Experience
A90: No | E90: Money. Also our child needs to learn to do things without his parents there. | F90: Cost / Finances | G90: Cost / Finances; Wants Child to Have Independent Experience
A91: No | E91: To the parent expo? I must not have been paying attention because I didn't know about it. | F91: Not Aware It Was an Option | G91: Not Aware It Was an Option
A92: No | E92: I want my son to learn that he can be independent of me and have his own experience | F92: Wants Child to Have Independent Experience | G92: Wants Child to Have Independent Experience
A93: No | E93: I wanted my daughter to have an independent experience | F93: Wants Child to Have Independent Experience | G93: Wants Child to Have Independent Experience
A94: Yes | B94: My daughter wouldn't go with me | C94: Concerned About Child Going Alone / Safety | D94: Concerned About Child Going Alone / Safety
A95: No | E95: learning to know and serve people who are having a different life experience from us. | F95: Wants Child to Have Independent Experience | G95: Wants Child to Have Independent Experience
A96: No | E96: cost and family responsibility at home | F96: Cost / Finances | G96: Cost / Finances; Work Schedule / Time Off
A97: No | E97: Cost mainly. Also, we want our child to have an experience away from family. | F97: Cost / Finances | G97: Cost / Finances; Other Kids / Family at Home; Wants Child to Have Independent Experience
A98: No | E98: My husband is going with our daughter instead | F98: Another Family Member Going Instead | G98: Another Family Member Going Instead
A99: No | E99: Time | F99: Work Schedule / Time Off | G99: Work Schedule / Time Off
A100: No | E100: money and time | F100: Cost / Finances | G100: Cost / Finances; Work Schedule / Time Off
...

Sheet Insights
A1: Status | B1: Reason To Go | C1: Reason To Go - Category | D1: Reason To Go - All Tags | E1: Reason Not To Go | F1: Reason Not To Go - Category | G1: Reason Not To Go - All Tags | H1: What Would Help | I1: Not Going - Controllability | J1: Not Going - Soft No Signal | K1: Not Going - Reason Stack Count | L1: Would Help - Category | M1: Would Help - All Tags
A2: No | E2: Good for my son to go without me. | F2: Wants Child to Have Independent Experience | G2: Wants Child to Have Independent Experience | I2: Family's Own Choice | J2: FALSE | K2: 1
A3: No | E3: Confidence in my kid | F3: Wants Child to Have Independent Experience | G3: Wants Child to Have Independent Experience | I3: Family's Own Choice | J3: FALSE | K3: 1
A4: No | E4: Not needed | F4: Not Needed | G4: Not Needed | I4: Family's Own Choice | J4: FALSE | K4: 1
A5: No | E5: I still have younger children to save for. | F5: Other Kids / Family at Home | G5: Other Kids / Family at Home | I5: Family's Own Choice | J5: FALSE | K5: 1
A6: No | E6: I think it is better for him | F6: Wants Child to Have Independent Experience | G6: Wants Child to Have Independent Experience | I6: Family's Own Choice | J6: FALSE | K6: 1
A7: No | E7: Want my son to have his own experience | F7: Wants Child to Have Independent Experience | G7: Wants Child to Have Independent Experience | I7: Family's Own Choice | J7: FALSE | K7: 1
A8: Yes | B8: I love teenagers, people in other cultures, and I love travel. | C8: Love of Travel / Culture | D8: Love of Travel / Culture | J8: FALSE | K8: 0
A9: Yes | B9: My husband wanted someone to go with our daughter, but I also wanted to experience this piece of heaven. I love teenagers! | C9: Wanted Shared Experience with Child | D9: Wanted Shared Experience with Child | J9: FALSE | K9: 0
A10: No | E10: The cost. Would have loved to go as a parent but it just wasn't in our budget | F10: Cost / Finances | G10: Cost / Finances | I10: HXP Can Directly Fix | J10: FALSE | K10: 1
A11: No | E11: Friends with experience | F11: Wants Child to Have Independent Experience | G11: Wants Child to Have Independent Experience | I11: Family's Own Choice | J11: FALSE | K11: 1
A12: Yes | B12: Could go with my son | C12: Other / Uncategorized | J12: FALSE | K12: 0
A13: No | E13: Time away from work | F13: Work Schedule / Time Off | G13: Work Schedule / Time Off | I13: HXP Can Influence | J13: FALSE | K13: 1
A14: No | E14: Thought my daughter would have a better experience with out me | F14: Wants Child to Have Independent Experience | G14: Wants Child to Have Independent Experience | I14: Family's Own Choice | J14: FALSE | K14: 1
A15: No | J15: FALSE | K15: 0
A16: No | J16: FALSE | K16: 0
A17: No | E17: Our son needs an independent experience. | F17: Wants Child to Have Independent Experience | G17: Wants Child to Have Independent Experience | I17: Family's Own Choice | J17: FALSE | K17: 1
A18: No | E18: Money | F18: Cost / Finances | G18: Cost / Finances | I18: HXP Can Directly Fix | J18: FALSE | K18: 1
A19: No | E19: I have 4 other kiddos at home that need me | F19: Other Kids / Family at Home | G19: Other Kids / Family at Home | I19: Family's Own Choice | J19: FALSE | K19: 1
A20: No | E20: cost | F20: Cost / Finances | G20: Cost / Finances | I20: HXP Can Directly Fix | J20: FALSE | K20: 1
A21: No | E21: my daughter does not want me to go | F21: Child Didn't Want Parent to Come | G21: Child Didn't Want Parent to Come | I21: Family's Own Choice | J21: FALSE | K21: 1
A22: No | E22: Wanted my son to go alone | F22: Wants Child to Have Independent Experience | G22: Wants Child to Have Independent Experience | I22: Family's Own Choice | J22: FALSE | K22: 1
A23: No | J23: FALSE | K23: 0
A24: Yes | B24: My daughter asked me ro go | C24: Child/Spouse Asked Them to Go | D24: Child/Spouse Asked Them to Go | J24: FALSE | K24: 0
A25: No | E25: I want to fill up my time with something fun that makes me happy and is productive. I am also excited to experience the beauty of OBX | F25: Work Schedule / Time Off | G25: Work Schedule / Time Off; Wants Child to Have Independent Experience | I25: HXP Can Influence | J25: FALSE | K25: 2
A26: No | E26: My job and time off. I would really love to go another year. | F26: Work Schedule / Time Off | G26: Work Schedule / Time Off | I26: HXP Can Influence | J26: TRUE | K26: 1
A27: No | E27: I wanted my daughter to have this experience on her own. I wanted her to rely on her group rather than me, to help her build stronger connections with other builders & the trip leaders. | F27: Wants Child to Have Independent Experience | G27: Wants Child to Have Independent Experience; Other Life Commitment | I27: Family's Own Choice | J27: FALSE | K27: 2
A28: No | E28: Younger kids at home | F28: Other Kids / Family at Home | G28: Other Kids / Family at Home | I28: Family's Own Choice | J28: FALSE | K28: 1
A29: No | E29: Daughter asked me not to go | F29: Child Didn't Want Parent to Come | G29: Child Didn't Want Parent to Come | I29: Family's Own Choice | J29: FALSE | K29: 1
A30: No | E30: I really wanted to go, my son was cool with me going, but the Spirit said he needed to do this without me. | F30: Wants Child to Have Independent Experience | G30: Wants Child to Have Independent Experience | I30: Family's Own Choice | J30: FALSE | K30: 1
A31: No | E31: Work schedule is not compatible with the HXP schedule. | F31: Work Schedule / Time Off | G31: Work Schedule / Time Off | I31: HXP Can Influence | J31: FALSE | K31: 1
A32: No | E32: Cost & time away from other kids, also excited for my son to do this without me | F32: Cost / Finances | G32: Cost / Finances; Work Schedule / Time Off; Other Kids / Family at Home; Wants Child to Have Independent Experience | I32: HXP Can Directly Fix | J32: FALSE | K32: 4
A33: Maybe | H33: Cost | J33: FALSE | K33: 0 | L33: Cost / Financial Assistance | M33: Cost / Financial Assistance
A34: No | E34: Private time for him | F34: Work Schedule / Time Off | G34: Work Schedule / Time Off | I34: HXP Can Influence | J34: FALSE | K34: 1
A35: No | E35: Work obligations | F35: Work Schedule / Time Off | G35: Work Schedule / Time Off | I35: HXP Can Influence | J35: FALSE | K35: 1
A36: No | E36: My child wanted to go on her own. | F36: Wants Child to Have Independent Experience | G36: Wants Child to Have Independent Experience | I36: Family's Own Choice | J36: FALSE | K36: 1
A37: Yes | B37: Previous trips | C37: Previous Positive Experience | D37: Previous Positive Experience | J37: FALSE | K37: 0
A38: No | E38: Time/ son coming home from a mission | F38: Work Schedule / Time Off | G38: Work Schedule / Time Off; Other Life Commitment | I38: HXP Can Influence | J38: FALSE | K38: 2
A39: Yes | B39: I have been before and love it. | C39: Previous Positive Experience | D39: Previous Positive Experience | J39: FALSE | K39: 0
A40: Yes | B40: The Q&A night | C40: Trust in the HXP Program | D40: Trust in the HXP Program | J40: FALSE | K40: 0
A41: No | E41: My husband is going as the male parent builder | F41: Another Family Member Going Instead | G41: Another Family Member Going Instead | I41: Family's Own Choice | J41: FALSE | K41: 1
A42: No | E42: Time and money | F42: Cost / Finances | G42: Cost / Finances; Work Schedule / Time Off | I42: HXP Can Directly Fix | J42: FALSE | K42: 2
A43: No | J43: FALSE | K43: 0
A44: No | E44: Just the timing with life and having other kids at home. | F44: Work Schedule / Time Off | G44: Work Schedule / Time Off; Other Kids / Family at Home | I44: HXP Can Influence | J44: FALSE | K44: 2
A45: No | E45: Other kids at home. | F45: Other Kids / Family at Home | G45: Other Kids / Family at Home | I45: Family's Own Choice | J45: FALSE | K45: 1
A46: No | E46: I want my son To have this experience alone. | F46: Wants Child to Have Independent Experience | G46: Wants Child to Have Independent Experience | I46: Family's Own Choice | J46: FALSE | K46: 1
A47: No | E47: Wanted my son to be on his own | F47: Wants Child to Have Independent Experience | G47: Wants Child to Have Independent Experience | I47: Family's Own Choice | J47: FALSE | K47: 1
A48: Maybe | H48: If it was less expensive | J48: FALSE | K48: 0 | L48: Cost / Financial Assistance | M48: Cost / Financial Assistance
A49: No | E49: I wanted my daughter to have an experience where she needed to learn to rely on herself instead of her parents | F49: Wants Child to Have Independent Experience | G49: Wants Child to Have Independent Experience | I49: Family's Own Choice | J49: FALSE | K49: 1
A50: No | E50: $$, otherwise, I'd love to go. We could only afford for our youth to go. | F50: Cost / Finances | G50: Cost / Finances | I50: HXP Can Directly Fix | J50: FALSE | K50: 1
A51: No | E51: I want my son to have an independent experience away from parents. | F51: Wants Child to Have Independent Experience | G51: Wants Child to Have Independent Experience | I51: Family's Own Choice | J51: FALSE | K51: 1
A52: No | J52: FALSE | K52: 0
A53: No | E53: My husband and I have both been trip builders before. Our son wanted the experience of going without parents :) | F53: Wants Child to Have Independent Experience | G53: Wants Child to Have Independent Experience | I53: Family's Own Choice | J53: FALSE | K53: 1
A54: No | E54: This is my son's experience. He always has his parents in tow on church functions. | F54: Wants Child to Have Independent Experience | G54: Wants Child to Have Independent Experience | I54: Family's Own Choice | J54: FALSE | K54: 1
A55: No | E55: My child wanted to go alone | F55: Wants Child to Have Independent Experience | G55: Wants Child to Have Independent Experience | I55: Family's Own Choice | J55: FALSE | K55: 1
A56: No | E56: My child | F56: Family's Own Choice (No Elaboration) | G56: Family's Own Choice (No Elaboration) | I56: Family's Own Choice | J56: FALSE | K56: 1
A57: No | E57: I think my daughter was excited to do this on her own - without her dad or I having to be part of it. | F57: Wants Child to Have Independent Experience | G57: Wants Child to Have Independent Experience | I57: Family's Own Choice | J57: FALSE | K57: 1
A58: No | E58: Timing & cost | F58: Cost / Finances | G58: Cost / Finances; Work Schedule / Time Off | I58: HXP Can Directly Fix | J58: FALSE | K58: 2
A59: No | E59: The expense | F59: Cost / Finances | G59: Cost / Finances | I59: HXP Can Directly Fix | J59: FALSE | K59: 1
A60: No | E60: My daughter really wanted to have an independent experience and go on her own. | F60: Wants Child to Have Independent Experience | G60: Wants Child to Have Independent Experience | I60: Family's Own Choice | J60: FALSE | K60: 1
A61: No | E61: Wanting to let my son have his own experience | F61: Wants Child to Have Independent Experience | G61: Wants Child to Have Independent Experience | I61: Family's Own Choice | J61: FALSE | K61: 1
A62: No | E62: Time and money | F62: Cost / Finances | G62: Cost / Finances; Work Schedule / Time Off | I62: HXP Can Directly Fix | J62: FALSE | K62: 2
A63: No | E63: Price | F63: Cost / Finances | G63: Cost / Finances | I63: HXP Can Directly Fix | J63: FALSE | K63: 1
A64: No | E64: Availability | F64: Work Schedule / Time Off | G64: Work Schedule / Time Off | I64: HXP Can Influence | J64: FALSE | K64: 1
A65: Maybe | J65: FALSE | K65: 0
A66: No | J66: FALSE | K66: 0
A67: No | E67: My little kids at home. | F67: Other Kids / Family at Home | G67: Other Kids / Family at Home | I67: Family's Own Choice | J67: FALSE | K67: 1
A68: No | E68: My child wanted to go alone and I have younger children | F68: Other Kids / Family at Home | G68: Other Kids / Family at Home; Wants Child to Have Independent Experience | I68: Family's Own Choice | J68: FALSE | K68: 2
A69: No | E69: Time away from work and wanted son to have his own experience. | F69: Work Schedule / Time Off | G69: Work Schedule / Time Off; Wants Child to Have Independent Experience | I69: HXP Can Influence | J69: FALSE | K69: 2
A70: Yes | B70: My wife went with our son last year. | C70: Previous Positive Experience | D70: Previous Positive Experience | J70: FALSE | K70: 0
A71: No | E71: Wanted my daughter to have as much autonomy while on her trip. | F71: Wants Child to Have Independent Experience | G71: Wants Child to Have Independent Experience | I71: Family's Own Choice | J71: FALSE | K71: 1
A72: Yes | B72: Desire to spend time with my daughter doing something important, memorable and impactful. | C72: Wanted Shared Experience with Child | D72: Wanted Shared Experience with Child | J72: FALSE | K72: 0
A73: No | E73: Work obligations | F73: Work Schedule / Time Off | G73: Work Schedule / Time Off | I73: HXP Can Influence | J73: FALSE | K73: 1
A74: No | E74: Work | F74: Work Schedule / Time Off | G74: Work Schedule / Time Off | I74: HXP Can Influence | J74: FALSE | K74: 1
A75: No | E75: My child needed to do this without a parent | F75: Wants Child to Have Independent Experience | G75: Wants Child to Have Independent Experience | I75: Family's Own Choice | J75: FALSE | K75: 1
A76: No | E76: I don't enjoy being responsible for other people's kids | F76: Not a Traveler / Personal Preference | G76: Not a Traveler / Personal Preference | I76: HXP Can Influence | J76: FALSE | K76: 1
A77: Yes | B77: Desire to spend time with my son and to have an adventure. | C77: Wanted Shared Experience with Child | D77: Wanted Shared Experience with Child; Love of Travel / Culture | J77: FALSE | K77: 0
A78: No | J78: FALSE | K78: 0
A79: No | E79: My daughter didn't want us to go | F79: Child Didn't Want Parent to Come | G79: Child Didn't Want Parent to Come | I79: Family's Own Choice | J79: FALSE | K79: 1
A80: No | E80: Personally not adventurous and comfortable | F80: Not a Traveler / Personal Preference | G80: Not a Traveler / Personal Preference | I80: HXP Can Influence | J80: FALSE | K80: 1
A81: Yes | B81: I wanted my son to go, and there was not a spot for him. The spot was freed up when I agreed to go as a parent builder. And I have a brother-in-law who went as a parent builder and had nothing but fantastic things to say about his experience. | C81: Wanted Shared Experience with Child | D81: Wanted Shared Experience with Child | J81: FALSE | K81: 0
A82: No | E82: We thought it would be a better experience for him to go alone | F82: Wants Child to Have Independent Experience | G82: Wants Child to Have Independent Experience | I82: Family's Own Choice | J82: FALSE | K82: 1
A83: No | E83: Big church callings have required us to always be at camps and other activities for our children. Our son needs a chance to be able to go out and experience life on his own without mom and dad there. | F83: Wants Child to Have Independent Experience | G83: Wants Child to Have Independent Experience; Other Life Commitment | I83: Family's Own Choice | J83: FALSE | K83: 2
A84: No | E84: Busy schedule | F84: Work Schedule / Time Off | G84: Work Schedule / Time Off | I84: HXP Can Influence | J84: FALSE | K84: 1
A85: No | E85: can't make it work with kids at home | F85: Work Schedule / Time Off | G85: Work Schedule / Time Off; Other Kids / Family at Home | I85: HXP Can Influence | J85: FALSE | K85: 2
A86: No | E86: We wanted our daughter to have an experience on her own, I have been at every camp etc she has been to. :) | F86: Wants Child to Have Independent Experience | G86: Wants Child to Have Independent Experience | I86: Family's Own Choice | J86: FALSE | K86: 1
A87: No | E87: Other kids at home | F87: Other Kids / Family at Home | G87: Other Kids / Family at Home | I87: Family's Own Choice | J87: FALSE | K87: 1
A88: No | E88: Not the right season of my life. I still have little kids at home. I also think for my particular child she will have a better experience on her own. | F88: Other Kids / Family at Home | G88: Other Kids / Family at Home; Wants Child to Have Independent Experience | I88: Family's Own Choice | J88: FALSE | K88: 2
A89: No | E89: Sibling had a great experience | F89: Other Kids / Family at Home | G89: Other Kids / Family at Home; Wants Child to Have Independent Experience | I89: Family's Own Choice | J89: FALSE | K89: 2
A90: No | E90: Money. Also our child needs to learn to do things without his parents there. | F90: Cost / Finances | G90: Cost / Finances; Wants Child to Have Independent Experience | I90: HXP Can Directly Fix | J90: FALSE | K90: 2
A91: No | E91: To the parent expo? I must not have been paying attention because I didn't know about it. | F91: Not Aware It Was an Option | G91: Not Aware It Was an Option | I91: HXP Can Directly Fix | J91: FALSE | K91: 1
A92: No | E92: I want my son to learn that he can be independent of me and have his own experience | F92: Wants Child to Have Independent Experience | G92: Wants Child to Have Independent Experience | I92: Family's Own Choice | J92: FALSE | K92: 1
A93: No | E93: I wanted my daughter to have an independent experience | F93: Wants Child to Have Independent Experience | G93: Wants Child to Have Independent Experience | I93: Family's Own Choice | J93: FALSE | K93: 1
A94: Yes | B94: My daughter wouldn't go with me | C94: Concerned About Child Going Alone / Safety | D94: Concerned About Child Going Alone / Safety | J94: FALSE | K94: 0
A95: No | E95: learning to know and serve people who are having a different life experience from us. | F95: Wants Child to Have Independent Experience | G95: Wants Child to Have Independent Experience | I95: Family's Own Choice | J95: FALSE | K95: 1
A96: No | E96: cost and family responsibility at home | F96: Cost / Finances | G96: Cost / Finances; Work Schedule / Time Off | I96: HXP Can Directly Fix | J96: FALSE | K96: 2
A97: No | E97: Cost mainly. Also, we want our child to have an experience away from family. | F97: Cost / Finances | G97: Cost / Finances; Other Kids / Family at Home; Wants Child to Have Independent Experience | I97: HXP Can Directly Fix | J97: FALSE | K97: 3
A98: No | E98: My husband is going with our daughter instead | F98: Another Family Member Going Instead | G98: Another Family Member Going Instead | I98: Family's Own Choice | J98: FALSE | K98: 1
A99: No | E99: Time | F99: Work Schedule / Time Off | G99: Work Schedule / Time Off | I99: HXP Can Influence | J99: FALSE | K99: 1
A100: No | E100: money and time | F100: Cost / Finances | G100: Cost / Finances; Work Schedule / Time Off | I100: HXP Can Directly Fix | J100: FALSE | K100: 2
...

Sheet Insights Summary
A1: Insight | B1: Metric | C1: Value
A2: 1. Controllability | B2: HXP Can Directly Fix | C2: 239
A3: 1. Controllability | B3: HXP Can Directly Fix (% of reasons given) | C3: 26.7
A4: 1. Controllability | B4: HXP Can Influence | C4: 222
A5: 1. Controllability | B5: HXP Can Influence (% of reasons given) | C5: 24.8
A6: 1. Controllability | B6: Family's Own Choice | C6: 418
A7: 1. Controllability | B7: Family's Own Choice (% of reasons given) | C7: 46.7
A8: 1. Controllability | B8: Unknown | C8: 17
A9: 1. Controllability | B9: Unknown (% of reasons given) | C9: 1.9
A10: 2. Soft No Signal | B10: Responses hinting at future interest | C10: 30
A11: 2. Soft No Signal | B11: % of 'No' reasons given | C11: 3.3
A12: 3. Reason Stack Count | B12: Single-theme responses | C12: 668
... A24: 4. Would-Help Themes | B24: Registration / Spot Availability | C24: 1
